python_orbeon_budget/__init__.py
python_orbeon_budget/budget.py
python_orbeon_budget/contents/logo.png
python_orbeon_budget/contents/signature.png
python_orbeon_budget/contents/stamp.png
python_orbeon_budget/contents/watermark.png
tests/__init__.py
tests/test_budget.py
python_orbeon_budget-1.0.11.dist-info/LICENSE
python_orbeon_budget-1.0.11.dist-info/METADATA
python_orbeon_budget-1.0.11.dist-info/WHEEL
python_orbeon_budget-1.0.11.dist-info/top_level.txt
python_orbeon_budget-1.0.11.dist-info/RECORD
