Metadata-Version: 2.1
Name: python-orbeon-budget
Version: 1.0.11
Summary: Uma biblioteca leve e independente para gerar orçamentos padronizados em formato PDF A4 a partir de um dicionário (context).
Home-page: https://github.com/getorbeon/python-orbeon-budget
Author: Edu Fontes
Author-email: eduramofo@gmail.com
License: UNKNOWN
Platform: UNKNOWN
Classifier: Programming Language :: Python :: 3
Classifier: License :: OSI Approved :: MIT License
Classifier: Operating System :: OS Independent
Requires-Python: >=3.10
License-File: LICENSE
Requires-Dist: pillow<11.2,>=11.1
Requires-Dist: reportlab
Provides-Extra: pycairo
Requires-Dist: reportlab[pycairo]; extra == "pycairo"
